pythonic_fp/splitends/__init__.py
pythonic_fp/splitends/__init__.pyi
pythonic_fp/splitends/py.typed
pythonic_fp/splitends/splitend.py
pythonic_fp/splitends/splitend.pyi
pythonic_fp/splitends/splitend_node.py
pythonic_fp/splitends/splitend_node.pyi
pythonic_fp_splitends-2.0.0.dist-info/licenses/LICENSE
pythonic_fp_splitends-2.0.0.dist-info/WHEEL
pythonic_fp_splitends-2.0.0.dist-info/METADATA
pythonic_fp_splitends-2.0.0.dist-info/RECORD
