Metadata-Version: 2.4
Name: pythonic-fp-splitends
Version: 2.0.0
Summary: Mutable stack objects that can safely share data.
Keywords: SplitEnd,lifo,stack
Author-email: "Geoffrey R. Scheller" <geoffrey@scheller.com>
Requires-Python: >=3.13
Classifier: Development Status :: 3 - Alpha
Classifier: Framework :: Pytest
Classifier: Intended Audience :: Developers
Classifier: License :: OSI Approved :: Apache Software License
Classifier: Operating System :: OS Independent
Classifier: Programming Language :: Python :: 3.13
Classifier: Typing :: Typed
License-File: LICENSE
Requires-Dist: pythonic-fp-fptools>=5.1.2
Requires-Dist: pythonic-fp-iterables>=5.1.2
Requires-Dist: pythonic-fp-queues>=5.1.0
Requires-Dist: pytest>=8.4.1 ; extra == "test"
Project-URL: Changelog, https://github.com/grscheller/pythonic-fp-splitends/blob/main/CHANGELOG.rst
Project-URL: Documentation, https://grscheller.github.io/pythonic-fp/splitends/development/build/html/
Project-URL: Homepage, https://grscheller.github.io/pythonic-fp/homepage/build/html/
Project-URL: Source, https://github.com/grscheller/pythonic-fp-splitends
Provides-Extra: test
